karrio/mappers/postat/__init__.py
karrio/mappers/postat/mapper.py
karrio/mappers/postat/proxy.py
karrio/mappers/postat/settings.py
karrio/plugins/postat/__init__.py
karrio/providers/postat/__init__.py
karrio/providers/postat/error.py
karrio/providers/postat/units.py
karrio/providers/postat/utils.py
karrio/providers/postat/shipment/__init__.py
karrio/providers/postat/shipment/cancel.py
karrio/providers/postat/shipment/create.py
karrio/schemas/postat/__init__.py
karrio/schemas/postat/plc_types.py
karrio/schemas/postat/void_types.py
karrio_postat-2026.1.4.dist-info/METADATA
karrio_postat-2026.1.4.dist-info/WHEEL
karrio_postat-2026.1.4.dist-info/entry_points.txt
karrio_postat-2026.1.4.dist-info/top_level.txt
karrio_postat-2026.1.4.dist-info/RECORD
